Workbook

Sheet Campaign Data
A1: Lead ID | B1: Date | C1: Customer Segment | D1: Region | E1: Campaign Channel | F1: Offer Type | G1: Opened? | H1: Clicked? | I1: Booked Demo? | J1: Converted? | K1: Campaign Cost | L1: Revenue | M1: Net Value | N1: Outcome
A2: LEAD-0001 | B2: 46144 | C2: Small Business | D2: West | E2: LinkedIn Ad | F2: Free Trial | G2: No | H2: No | I2: No | J2: No | K2: 26.24 | L2: 0 | M2: -26.24 | N2: No Engagement
A3: LEAD-0002 | B3: 46151 | C3: Education | D3: South | E3: Search Ad | F3: Demo | G3: Yes | H3: No | I3: No | J3: No | K3: 19.19 | L3: 0 | M3: -19.19 | N3: Opened Only
A4: LEAD-0003 | B4: 46128 | C4: Non-Profit | D4: North | E4: Email | F4: Free Trial | G4: Yes | H4: No | I4: No | J4: No | K4: 12.8 | L4: 0 | M4: -12.8 | N4: Opened Only
A5: LEAD-0004 | B5: 46120 | C5: Non-Profit | D5: South | E5: Email | F5: Demo | G5: No | H5: No | I5: No | J5: No | K5: 11.12 | L5: 0 | M5: -11.12 | N5: No Engagement
A6: LEAD-0005 | B6: 46114 | C6: Small Business | D6: North | E6: Search Ad | F6: Consultation | G6: No | H6: No | I6: No | J6: No | K6: 32.09 | L6: 0 | M6: -32.09 | N6: No Engagement
A7: LEAD-0006 | B7: 46124 | C7: Corporate | D7: South | E7: LinkedIn Ad | F7: Discount | G7: Yes | H7: Yes | I7: No | J7: Yes | K7: 39.91 | L7: 1178.55 | M7: 1138.64 | N7: Converted
A8: LEAD-0007 | B8: 46130 | C8: Small Business | D8: North | E8: LinkedIn Ad | F8: Free Trial | G8: Yes | H8: Yes | I8: Yes | J8: Yes | K8: 34.94 | L8: 663.71 | M8: 628.77 | N8: Converted
A9: LEAD-0008 | B9: 46150 | C9: Education | D9: East | E9: Webinar | F9: Free Trial | G9: Yes | H9: No | I9: No | J9: No | K9: 44.52 | L9: 0 | M9: -44.52 | N9: Opened Only
A10: LEAD-0009 | B10: 46156 | C10: Corporate | D10: West | E10: Email | F10: Demo | G10: No | H10: No | I10: No | J10: No | K10: 10.67 | L10: 0 | M10: -10.67 | N10: No Engagement
A11: LEAD-0010 | B11: 46142 | C11: Education | D11: West | E11: Email | F11: Free Trial | G11: Yes | H11: No | I11: No | J11: No | K11: 14.58 | L11: 0 | M11: -14.58 | N11: Opened Only
A12: LEAD-0011 | B12: 46120 | C12: Non-Profit | D12: South | E12: Email | F12: Consultation | G12: No | H12: No | I12: No | J12: No | K12: 12.77 | L12: 0 | M12: -12.77 | N12: No Engagement
A13: LEAD-0012 | B13: 46154 | C13: Corporate | D13: South | E13: Email | F13: Discount | G13: No | H13: No | I13: No | J13: No | K13: 11.92 | L13: 0 | M13: -11.92 | N13: No Engagement
... A181: LEAD-0180 | B181: 46138 | C181: Corporate | D181: South | E181: Search Ad | F181: Free Trial | G181: Yes | H181: No | I181: No | J181: No | K181: 31.8 | L181: 0 | M181: -31.8 | N181: Opened Only

Sheet IRI_UO_WorkspaceStorage
A3: WORKBOOK_ATTRIBUTE | B3: Label5
A4: UO_REPORT_LIST | B4: Label4
A5: 2b5ab646be864a65a4af09f6e2ccbf75 | B5: Label3
A6: 2b5ab646be864a65a4af09f6e2ccbf75|SELECTED_DIM | B6: Label2
A7: 2b5ab646be864a65a4af09f6e2ccbf75|PAGEKEY|:1_Category:3760338|d6daaffa6b44e953:550d9f90:19ff00ba3ce:-5133 | B7: Label1

Sheet Answers
A3: Q1. Probability randomly selected lead clicks campaign
A4: =COUNTIF(CampaignData[Clicked?],"Yes")/COUNTA(CampaignData[Lead ID]) -> 0.17777778
A8: Q2. Probability a lead clicked the campaign and booked a demo
A9: =COUNTIFS(CampaignData[Clicked?],"Yes",CampaignData[Booked Demo?],"Yes")/COUNTA(CampaignData[Lead ID]) -> 0.1
A13: Q3. Expected Value by Campaign Channel
A15: Outcome | C15: Email | D15: Webinar | E15: LinkedIn Ad | F15: Search Ad
A16: Converted | B16: Probability | C16: =COUNTIFS(CampaignData[Campaign Channel],Answers!C$15,CampaignData[Outcome],$A16)/COUNTIF(CampaignData[Campaign Channel],C$15) -> 0.066666667 | D16: =COUNTIFS(CampaignData[Campaign Channel],Answers!D$15,CampaignData[Outcome],$A16)/COUNTIF(CampaignData[Campaign Channel],D$15) -> 0.25 | E16: =COUNTIFS(CampaignData[Campaign Channel],Answers!E$15,CampaignData[Outcome],$A16)/COUNTIF(CampaignData[Campaign Channel],E$15) -> 0.090909091 | F16: =COUNTIFS(CampaignData[Campaign Channel],Answers!F$15,CampaignData[Outcome],$A16)/COUNTIF(CampaignData[Campaign Channel],F$15) -> 0.090909091
A17: Booked Demo | C17: =COUNTIFS(CampaignData[Campaign Channel],Answers!C$15,CampaignData[Outcome],$A17)/COUNTIF(CampaignData[Campaign Channel],C$15) -> 0 | D17: =COUNTIFS(CampaignData[Campaign Channel],Answers!D$15,CampaignData[Outcome],$A17)/COUNTIF(CampaignData[Campaign Channel],D$15) -> 0.03125 | E17: =COUNTIFS(CampaignData[Campaign Channel],Answers!E$15,CampaignData[Outcome],$A17)/COUNTIF(CampaignData[Campaign Channel],E$15) -> 0.018181818 | F17: =COUNTIFS(CampaignData[Campaign Channel],Answers!F$15,CampaignData[Outcome],$A17)/COUNTIF(CampaignData[Campaign Channel],F$15) -> 0
A18: Clicked | C18: =COUNTIFS(CampaignData[Campaign Channel],Answers!C$15,CampaignData[Outcome],$A18)/COUNTIF(CampaignData[Campaign Channel],C$15) -> 0.066666667 | D18: =COUNTIFS(CampaignData[Campaign Channel],Answers!D$15,CampaignData[Outcome],$A18)/COUNTIF(CampaignData[Campaign Channel],D$15) -> 0.0625 | E18: =COUNTIFS(CampaignData[Campaign Channel],Answers!E$15,CampaignData[Outcome],$A18)/COUNTIF(CampaignData[Campaign Channel],E$15) -> 0.072727273 | F18: =COUNTIFS(CampaignData[Campaign Channel],Answers!F$15,CampaignData[Outcome],$A18)/COUNTIF(CampaignData[Campaign Channel],F$15) -> 0
A19: Opened Only | C19: =COUNTIFS(CampaignData[Campaign Channel],Answers!C$15,CampaignData[Outcome],$A19)/COUNTIF(CampaignData[Campaign Channel],C$15) -> 0.4 | D19: =COUNTIFS(CampaignData[Campaign Channel],Answers!D$15,CampaignData[Outcome],$A19)/COUNTIF(CampaignData[Campaign Channel],D$15) -> 0.34375 | E19: =COUNTIFS(CampaignData[Campaign Channel],Answers!E$15,CampaignData[Outcome],$A19)/COUNTIF(CampaignData[Campaign Channel],E$15) -> 0.27272727 | F19: =COUNTIFS(CampaignData[Campaign Channel],Answers!F$15,CampaignData[Outcome],$A19)/COUNTIF(CampaignData[Campaign Channel],F$15) -> 0.33333333
A20: No Engagement | C20: =COUNTIFS(CampaignData[Campaign Channel],Answers!C$15,CampaignData[Outcome],$A20)/COUNTIF(CampaignData[Campaign Channel],C$15) -> 0.46666667 | D20: =COUNTIFS(CampaignData[Campaign Channel],Answers!D$15,CampaignData[Outcome],$A20)/COUNTIF(CampaignData[Campaign Channel],D$15) -> 0.3125 | E20: =COUNTIFS(CampaignData[Campaign Channel],Answers!E$15,CampaignData[Outcome],$A20)/COUNTIF(CampaignData[Campaign Channel],E$15) -> 0.54545455 | F20: =COUNTIFS(CampaignData[Campaign Channel],Answers!F$15,CampaignData[Outcome],$A20)/COUNTIF(CampaignData[Campaign Channel],F$15) -> 0.57575758
A24: Converted | B24: Avg. Net Value | C24: =IFERROR(AVERAGEIFS(CampaignData[Net Value],CampaignData[Campaign Channel],Answers!C$15,CampaignData[Outcome],$A24),0) -> 506.735 | D24: =IFERROR(AVERAGEIFS(CampaignData[Net Value],CampaignData[Campaign Channel],Answers!D$15,CampaignData[Outcome],$A24),0) -> 1226.9325 | E24: =IFERROR(AVERAGEIFS(CampaignData[Net Value],CampaignData[Campaign Channel],Answers!E$15,CampaignData[Outcome],$A24),0) -> 684.164 | F24: =IFERROR(AVERAGEIFS(CampaignData[Net Value],CampaignData[Campaign Channel],Answers!F$15,CampaignData[Outcome],$A24),0) -> 657.66667
A25: Booked Demo | C25: =IFERROR(AVERAGEIFS(CampaignData[Net Value],CampaignData[Campaign Channel],Answers!C$15,CampaignData[Outcome],$A25),0) -> 0 | D25: =IFERROR(AVERAGEIFS(CampaignData[Net Value],CampaignData[Campaign Channel],Answers!D$15,CampaignData[Outcome],$A25),0) -> -50.29 | E25: =IFERROR(AVERAGEIFS(CampaignData[Net Value],CampaignData[Campaign Channel],Answers!E$15,CampaignData[Outcome],$A25),0) -> -37.2 | F25: =IFERROR(AVERAGEIFS(CampaignData[Net Value],CampaignData[Campaign Channel],Answers!F$15,CampaignData[Outcome],$A25),0) -> 0
A26: Clicked | C26: =IFERROR(AVERAGEIFS(CampaignData[Net Value],CampaignData[Campaign Channel],Answers!C$15,CampaignData[Outcome],$A26),0) -> -11.9475 | D26: =IFERROR(AVERAGEIFS(CampaignData[Net Value],CampaignData[Campaign Channel],Answers!D$15,CampaignData[Outcome],$A26),0) -> -69.835 | E26: =IFERROR(AVERAGEIFS(CampaignData[Net Value],CampaignData[Campaign Channel],Answers!E$15,CampaignData[Outcome],$A26),0) -> -32.4975 | F26: =IFERROR(AVERAGEIFS(CampaignData[Net Value],CampaignData[Campaign Channel],Answers!F$15,CampaignData[Outcome],$A26),0) -> 0
A27: Opened Only | C27: =IFERROR(AVERAGEIFS(CampaignData[Net Value],CampaignData[Campaign Channel],Answers!C$15,CampaignData[Outcome],$A27),0) -> -14.547083 | D27: =IFERROR(AVERAGEIFS(CampaignData[Net Value],CampaignData[Campaign Channel],Answers!D$15,CampaignData[Outcome],$A27),0) -> -56.921818 | E27: =IFERROR(AVERAGEIFS(CampaignData[Net Value],CampaignData[Campaign Channel],Answers!E$15,CampaignData[Outcome],$A27),0) -> -30.202667 | F27: =IFERROR(AVERAGEIFS(CampaignData[Net Value],CampaignData[Campaign Channel],Answers!F$15,CampaignData[Outcome],$A27),0) -> -27.870909
A28: No Engagement | C28: =IFERROR(AVERAGEIFS(CampaignData[Net Value],CampaignData[Campaign Channel],Answers!C$15,CampaignData[Outcome],$A28),0) -> -13.646786 | D28: =IFERROR(AVERAGEIFS(CampaignData[Net Value],CampaignData[Campaign Channel],Answers!D$15,CampaignData[Outcome],$A28),0) -> -53.123 | E28: =IFERROR(AVERAGEIFS(CampaignData[Net Value],CampaignData[Campaign Channel],Answers!E$15,CampaignData[Outcome],$A28),0) -> -32.317667 | F28: =IFERROR(AVERAGEIFS(CampaignData[Net Value],CampaignData[Campaign Channel],Answers!F$15,CampaignData[Outcome],$A28),0) -> -27.089474
A31: Expected Value | C31: =SUMPRODUCT(C16:C20,C24:C28) -> 20.7985 | D31: =SUMPRODUCT(D16:D20,D24:D28) -> 264.62906 | E31: =SUMPRODUCT(E16:E20,E24:E28) -> 33.292 | F31: =SUMPRODUCT(F16:F20,F24:F28) -> 34.900606
